zotmd/__init__.py
zotmd/cli.py
zotmd/config.py
zotmd/py.typed
zotmd/core/__init__.py
zotmd/core/state_manager.py
zotmd/core/sync_engine.py
zotmd/core/zotero_client.py
zotmd/file_ops/__init__.py
zotmd/file_ops/file_manager.py
zotmd/models/__init__.py
zotmd/models/annotation.py
zotmd/models/item.py
zotmd/templates/__init__.py
zotmd/templates/default.md.j2
zotmd/templates/renderer.py
zotmd/utils/__init__.py
zotmd/utils/citation_key.py
zotmd/utils/color_mapper.py
zotmd/utils/date_formatter.py
zotmd/utils/filename_sanitizer.py
zotmd-0.2.0.dist-info/METADATA
zotmd-0.2.0.dist-info/WHEEL
zotmd-0.2.0.dist-info/entry_points.txt
zotmd-0.2.0.dist-info/licenses/LICENSE
zotmd-0.2.0.dist-info/RECORD
