Metadata-Version: 2.4
Name: zotmd
Version: 0.2.0
Summary: Add your description here
Author-email: Adhithya Bhaskar <adhithyabhaskar@gmail.com>
License-File: LICENSE
Requires-Python: >=3.13
Requires-Dist: alive-progress>=3.3.0
Requires-Dist: click>=8.3.1
Requires-Dist: jinja2>=3.1.6
Requires-Dist: platformdirs>=4.5.1
Requires-Dist: pyzotero>=1.7.6
